README.md
setup.py
arcadia/__init__.py
arcadia/arcadia.py
arcadia/errors.py
arcadia/setup.py
pyarcadia.egg-info/PKG-INFO
pyarcadia.egg-info/SOURCES.txt
pyarcadia.egg-info/dependency_links.txt
pyarcadia.egg-info/requires.txt
pyarcadia.egg-info/top_level.txt