Metadata-Version: 1.1
Name: pyarcadia
Version: 1.0.1
Summary: An arcadia-api wrapper built for python3+
Home-page: https://github.com/Zenrac/arcadia.py
Author: Zenrac
Author-email: zenrac@outlook.fr
License: UNKNOWN
Download-URL: https://github.com/Zenrac/arcadia.py/archive/1.0.1.tar.gz
Keywords: arcadia
Platform: UNKNOWN
